Metadata-Version: 2.1
Name: c8-source-postgres
Version: 0.0.12
Summary: C8 Source for extracting data from PostgresSQL.
Home-page: https://github.com/Macrometacorp/c8-source-postgres
Author: Macrometa
Classifier: License :: OSI Approved :: GNU Affero General Public License v3
Classifier: Programming Language :: Python :: 3 :: Only
License-File: LICENSE
Requires-Dist: pipelinewise-singer-python (==1.2.0)
Requires-Dist: psycopg2-binary (==2.9.3)
Requires-Dist: strict-rfc3339 (==0.7)
Requires-Dist: c8connector (==0.0.10)
Provides-Extra: test
Requires-Dist: pytest (==7.0.1) ; extra == 'test'
Requires-Dist: pylint (==2.12.*) ; extra == 'test'
Requires-Dist: pytest-cov (==4.0.0) ; extra == 'test'
